MANIFEST.in
README.md
setup.py
YmmuimLibrary/__init__.py
YmmuimLibrary/version.py
YmmuimLibrary.egg-info/PKG-INFO
YmmuimLibrary.egg-info/SOURCES.txt
YmmuimLibrary.egg-info/dependency_links.txt
YmmuimLibrary.egg-info/requires.txt
YmmuimLibrary.egg-info/top_level.txt
YmmuimLibrary.egg-info/zip-safe
YmmuimLibrary/__pycache__/__init__.cpython-37.pyc
YmmuimLibrary/__pycache__/version.cpython-37.pyc
YmmuimLibrary/action/__init__.py
YmmuimLibrary/action/actioner.py
YmmuimLibrary/action/__pycache__/__init__.cpython-37.pyc
YmmuimLibrary/action/__pycache__/actioner.cpython-37.pyc
YmmuimLibrary/keywords/__init__.py
YmmuimLibrary/keywords/_element.py
YmmuimLibrary/keywords/keywordgroup.py
YmmuimLibrary/keywords/__pycache__/__init__.cpython-37.pyc
YmmuimLibrary/keywords/__pycache__/_element.cpython-37.pyc
YmmuimLibrary/keywords/__pycache__/keywordgroup.cpython-37.pyc