Metadata-Version: 2.1
Name: YmmuimLibrary
Version: 0.0.2
Summary: YmmuimLibrary is a Mobile App testing library for Robot Framework, in Python3
Home-page: https://pypi.org/project/YmmuimLibrary/#description
Author: goblinintree
Author-email: goblinintree@126.com
License: MIT
Keywords: Appium,Robot Framework,YmmuimLibrary
Platform: all
Classifier: Environment :: Web Environment
Classifier: License :: OSI Approved :: MIT License
Classifier: Operating System :: Microsoft
Classifier: Programming Language :: Python :: 3.7
